README.rst
setup.py
conf_reader/__init__.py
conf_reader/singleton.py
ini_config_reader.egg-info/PKG-INFO
ini_config_reader.egg-info/SOURCES.txt
ini_config_reader.egg-info/dependency_links.txt
ini_config_reader.egg-info/top_level.txt