Metadata-Version: 1.1
Name: ini-config-reader
Version: 0.0.3
Summary: A simple config reader based on python Config Parser.
Home-page: https://github.com/teitiago/ini-config-reader
Author: Tiago Teixeira
Author-email: teitiago@gmail.com
License: UNKNOWN
Keywords: configuration ini reader
Platform: UNKNOWN
Classifier: Development Status :: 3 - Alpha
Classifier: Intended Audience :: Developers
Classifier: License :: OSI Approved :: MIT License
Classifier: Programming Language :: Python :: 3.5
Classifier: Programming Language :: Python :: 3.6
Classifier: Programming Language :: Python :: 3.7
